sxbutils/__init__.py
sxbutils/envvar.py
sxbutils/sxbutils.py
sxbutils/test.py
sxbutils-0.0.14.dist-info/LICENSE
sxbutils-0.0.14.dist-info/METADATA
sxbutils-0.0.14.dist-info/WHEEL
sxbutils-0.0.14.dist-info/top_level.txt
sxbutils-0.0.14.dist-info/RECORD
