Metadata-Version: 2.1
Name: sxbutils
Version: 0.0.14
Summary: Some utilities.
Home-page: https://bitbucket.org/sbotham/sxbutils/src/master/
Author: Steve Botham
Author-email: sbotham1968@gmail.com
License: MIT
Platform: UNKNOWN
Classifier: Development Status :: 4 - Beta
Classifier: License :: OSI Approved :: MIT License
Classifier: Programming Language :: Python
Classifier: Programming Language :: Python :: 3.5
Classifier: Programming Language :: Python :: 3.6
Classifier: Topic :: Software Development :: Libraries
Classifier: Topic :: Software Development :: Libraries :: Python Modules
Classifier: Intended Audience :: Developers
Requires-Python: >=3.5
License-File: LICENSE
Requires-Dist: requests
